cropharvest/__init__.py
cropharvest/bands.py
cropharvest/bbox.py
cropharvest/columns.py
cropharvest/config.py
cropharvest/countries.py
cropharvest/crops.py
cropharvest/datasets.py
cropharvest/engineer.py
cropharvest/inference.py
cropharvest/utils.py
cropharvest/country_shapefile/ne_50m_admin_0_countries.dbf
cropharvest/country_shapefile/ne_50m_admin_0_countries.shp
cropharvest/country_shapefile/ne_50m_admin_0_countries.shx
cropharvest/eo/__init__.py
cropharvest/eo/ee_boundingbox.py
cropharvest/eo/eo.py
cropharvest/eo/era5.py
cropharvest/eo/sentinel1.py
cropharvest/eo/sentinel2.py
cropharvest/eo/srtm.py
cropharvest/eo/utils.py
cropharvest-0.7.0.dist-info/LICENSE.txt
cropharvest-0.7.0.dist-info/METADATA
cropharvest-0.7.0.dist-info/WHEEL
cropharvest-0.7.0.dist-info/top_level.txt
cropharvest-0.7.0.dist-info/RECORD
