Metadata-Version: 2.1
Name: cropharvest
Version: 0.7.0
Summary: Open source remote sensing dataset with benchmarks
Home-page: https://github.com/nasaharvest/cropharvest
Author: Gabriel Tseng
Author-email: gabrieltseng95@gmail.com
Classifier: Programming Language :: Python :: 3
Classifier: License :: Other/Proprietary License
Classifier: Operating System :: OS Independent
Requires-Python: >=3.6
License-File: LICENSE.txt
Requires-Dist: pandas <2.0.0
Requires-Dist: geopandas ==0.9.0
Requires-Dist: xarray <0.20.0,>=0.16.2
Requires-Dist: tqdm >=4.61.1
Requires-Dist: h5py !=3.7.0,>=3.1.0
Requires-Dist: rasterio >=1.2.6
Requires-Dist: openpyxl >=2.5.9
Requires-Dist: scikit-learn >=0.22.2
